OpenMiChroM/ChromDynamics.py
OpenMiChroM/CndbTools.py
OpenMiChroM/Optimization.py
OpenMiChroM/__init__.py
tests/__init__.py
tests/tests.py
OpenMiChroM-0.0.3.dist-info/LICENSE
OpenMiChroM-0.0.3.dist-info/METADATA
OpenMiChroM-0.0.3.dist-info/WHEEL
OpenMiChroM-0.0.3.dist-info/entry_points.txt
OpenMiChroM-0.0.3.dist-info/top_level.txt
OpenMiChroM-0.0.3.dist-info/zip-safe
OpenMiChroM-0.0.3.dist-info/RECORD
